{
  "ngày": "day",
  "tuần": "week",
  "tháng": "month",
  "năm": "year",
  "hôm qua": "daysago",
  "ngày hôm qua": "daysago",
  "ngày mai": "nextday",
  "mai": "nextday",
  "hôm nay": "today",
  "ngày hôm nay": "today",
  "nay": "today",
  "hôm này": "today",
  "hôm kia": "beforeyesterday",
  "ngày kia": "aftertomorrow",
  "ngày qua": "daysago",
  "hôm trước": "daysago",
  "ngày trước": "daysago",
  "ngày tới": "nextday",
  "hôm tới": "nextday",
  "tuần trước": "lastweek",
  "tuần tới": "nextweek",
  "tuần sau": "nextweek",
  "tuần này": "thisweek",
  "tháng tới": "nextmonth",
  "tháng sau": "nextmonth",
  "tháng trước": "lastmonth",
  "tháng này": "thismonth",
  "năm sau": "nextyear",
  "năm tới": "nextyear",
  "năm ngoái": "lastyear",
  "năm trước": "lastyear",
  "năm nay": "thisyear",
  "thứ 2": "weekday2",
  "thứ hai": "weekday2",
  "thứ 3": "weekday3",
  "thứ ba": "weekday3",
  "thứ 4": "weekday4",
  "thứ tư": "weekday4",
  "thứ 5": "weekday5",
  "thứ năm": "weekday5",
  "thứ 6": "weekday6",
  "thứ sáu": "weekday6",
  "thứ 7": "weekday7",
  "thứ bảy": "weekday7",
  "chủ nhật": "weekday8",
  "tháng 1": "month1",
  "tháng một": "month1",
  "tháng 2": "month2",
  "tháng hai": "month2",
  "tháng 3": "month3",
  "tháng ba": "month3",
  "tháng 4": "month4",
  "tháng bốn": "month4",
  "tháng 5": "month5",
  "tháng năm": "month5",
  "tháng 6": "month6",
  "tháng sáu": "month6",
  "tháng 7": "month7",
  "tháng bảy": "month7",
  "tháng 8": "month8",
  "tháng tám": "month8",
  "tháng 9": "month9",
  "tháng chín": "month9",
  "tháng 10": "month10",
  "tháng mười": "month10",
  "tháng 11": "month11",
  "tháng mười một": "month11",
  "tháng 12": "month12",
  "tháng mười hai": "month12",
  "ngày 1": "day1",
  "mùng 1": "day1",
  "ngày 2": "day2",
  "mùng 2": "day2",
  "ngày 3": "day3",
  "mùng 3": "day3",
  "ngày 4": "day4",
  "mùng 4": "day4",
  "ngày 5": "day5",
  "mùng 5": "day5",
  "ngày 6": "day6",
  "mùng 6": "day6",
  "ngày 7": "day7",
  "mùng 7": "day7",
  "ngày 8": "day8",
  "mùng 8": "day8",
  "ngày 9": "day9",
  "mùng 9": "day9",
  "ngày 10": "day10",
  "mùng 10": "day10",
  "ngày 11": "day11",
  "ngày 12": "day12",
  "ngày 13": "day13",
  "ngày 14": "day14",
  "ngày 15": "day15",
  "ngày 16": "day16",
  "ngày 17": "day17",
  "ngày 18": "day18",
  "ngày 19": "day19",
  "ngày 20": "day20",
  "ngày 21": "day21",
  "ngày 22": "day22",
  "ngày 23": "day23",
  "ngày 24": "day24",
  "ngày 25": "day25",
  "ngày 26": "day26",
  "ngày 27": "day27",
  "ngày 28": "day28",
  "ngày 29": "day29",
  "ngày 30": "day30"
}